buildnumber/__init__.py
buildnumber/__main__.py
buildnumber/constants.py
buildnumber/exceptions.py
buildnumber/objects.py
buildnumber-1.0.6.dist-info/LICENSE.txt
buildnumber-1.0.6.dist-info/METADATA
buildnumber-1.0.6.dist-info/WHEEL
buildnumber-1.0.6.dist-info/entry_points.txt
buildnumber-1.0.6.dist-info/top_level.txt
buildnumber-1.0.6.dist-info/RECORD
