Metadata-Version: 2.1
Name: buildnumber
Version: 1.0.6
Summary: buildnumber is tool to control your build number.
Home-page: https://github.com/simonski/buildnumber
Author: Simon Gauld
Author-email: simon.gauld@gmail.com
License: Apache 2.0
Keywords: buildnumber setuptools development
Classifier: Development Status :: 3 - Alpha
Classifier: Programming Language :: Python :: 3.7
License-File: LICENSE.txt
Requires-Dist: PyYAML (==5.4)
Requires-Dist: simonski-pycommon
